setup.py
probability_distributions_322/test.py
probability_distributions_322.egg-info/PKG-INFO
probability_distributions_322.egg-info/SOURCES.txt
probability_distributions_322.egg-info/dependency_links.txt
probability_distributions_322.egg-info/not-zip-safe
probability_distributions_322.egg-info/top_level.txt