Metadata-Version: 1.0
Name: probability-distributions-322
Version: 1.2
Summary: Gaussian and Binomial distributions
Home-page: UNKNOWN
Author: Muhammad Qasim Khan
Author-email: qasimkhan3.124@gmail.com
License: UNKNOWN
Platform: UNKNOWN
